LICENSE
MANIFEST.in
README.rst
setup.cfg
setup.py
django_geonames_cities.egg-info/PKG-INFO
django_geonames_cities.egg-info/SOURCES.txt
django_geonames_cities.egg-info/dependency_links.txt
django_geonames_cities.egg-info/requires.txt
django_geonames_cities.egg-info/top_level.txt
geonames/__init__.py
geonames/api.py
geonames/apps.py
geonames/downloader.py
geonames/models.py
geonames/tests.py
geonames/urlsapi.py
geonames/management/commands/country_it_codice_catastale.py
geonames/management/commands/synchgeonames.py
geonames/management/commands/synchgeonamescountries.py
geonames/migrations/0001_initial.py
geonames/migrations/0002_fixtures.py
geonames/migrations/0003_geonamesadm3_it_codice_istat_alter_country_id_and_more.py
geonames/migrations/__init__.py